pyogctest/__init__.py
pyogctest/cli.py
pyogctest/data/__init__.py
pyogctest/data/data-wms-1.3.0.zip
pyogctest/data/data.py
pyogctest/data/teamengine_wms_130.qgs
pyogctest/logger.py
pyogctest/report/__init__.py
pyogctest/report/format.py
pyogctest/report/ogcapif/__init__.py
pyogctest/report/ogcapif/logo.png
pyogctest/report/ogcapif/ogcapif.py
pyogctest/report/ogcapif/style.css
pyogctest/report/ogcapif/template.html
pyogctest/report/report.py
pyogctest/report/wms130/__init__.py
pyogctest/report/wms130/logo.png
pyogctest/report/wms130/style.css
pyogctest/report/wms130/tohtml.xsl
pyogctest/report/wms130/wms130.py
pyogctest/teamengine.py
pyogctest-1.1.3.dist-info/LICENSE
pyogctest-1.1.3.dist-info/METADATA
pyogctest-1.1.3.dist-info/WHEEL
pyogctest-1.1.3.dist-info/entry_points.txt
pyogctest-1.1.3.dist-info/RECORD
