Metadata-Version: 2.3
Name: pyogctest
Version: 1.1.3
Summary: Python tool to run OGC test suites from cli
Author: Paul Blottiere
Author-email: blottiere.paul@gmail.com
Requires-Python: >=3.9
Classifier: Programming Language :: Python :: 3
Classifier: Programming Language :: Python :: 3.9
Classifier: Programming Language :: Python :: 3.10
Classifier: Programming Language :: Python :: 3.11
Classifier: Programming Language :: Python :: 3.12
Classifier: Programming Language :: Python :: 3.13
Requires-Dist: coloredlogs (>=15.0.1,<16.0.0)
Requires-Dist: docker (>=7.1.0,<8.0.0)
Requires-Dist: requests (>=2.32.3,<3.0.0)
Project-URL: Homepage, https://github.com/pblottiere/pyogctest
Project-URL: Issues, https://github.com/pblottiere/pyogctest/issues
